pyconfig_util/__init__.py
pyconfig_util/config_util.py
pyconfig_util-1.1.0.dist-info/LICENSE
pyconfig_util-1.1.0.dist-info/METADATA
pyconfig_util-1.1.0.dist-info/WHEEL
pyconfig_util-1.1.0.dist-info/top_level.txt
pyconfig_util-1.1.0.dist-info/zip-safe
pyconfig_util-1.1.0.dist-info/RECORD
