Metadata-Version: 2.1
Name: pyconfig_util
Version: 1.1.0
Summary: config助手
Home-page: https://github.com/buyfakett
Author: buyfakett
Author-email: buyfakett@vip.qq.com
License: MIT
Requires-Python: >=3.6
License-File: LICENSE
Requires-Dist: pyyaml
Requires-Dist: pyinitlog-util ==1.0.0
